{"data_details": {"data_name": "1_phase_to_ground", "attack_type": "fgsm", "model_params": {"model_input": [1, 64, 1], "learning_rate": 0.01, "n_epochs": 50, "batch_size": 256, "X_train_path": "/content/drive/MyDrive/MASc/Thesis/Quantum/Robustness Project/Datasets/1_phase_to_ground/PCA/X_train_PCA_6_noGaussian.npy", "y_train_path": "/content/drive/MyDrive/MASc/Thesis/Quantum/Robustness Project/Datasets/1_phase_to_ground/1_phase_to_ground_y_train.npy", "X_test_path": "/content/drive/MyDrive/MASc/Thesis/Quantum/Robustness Project/Datasets/1_phase_to_ground/PCA/X_test_PCA_6_noGaussian.npy", "y_test_path": "/content/drive/MyDrive/MASc/Thesis/Quantum/Robustness Project/Datasets/1_phase_to_ground/1_phase_to_ground_y_test.npy", "X_train_original_path": "/content/drive/MyDrive/MASc/Thesis/Quantum/Robustness Project/Datasets/1_phase_to_ground/1_phase_to_ground_X_train.npy", "X_test_original_path": "/content/drive/MyDrive/MASc/Thesis/Quantum/Robustness Project/Datasets/1_phase_to_ground/1_phase_to_ground_X_test.npy", "X_train_mean": [8.331698532047965e-16, 9.054708927381135e-16, 3.300158177517291e-17, -6.125751830046584e-17, 3.054314183902374e-17, 1.5388877754999767e-18], "X_train_std": [17.467028897817652, 15.403390694477219, 3.358527186953784, 1.6847570101478921, 1.3862410324653323, 0.8301834767752618], "standard_scaler_path": "/content/drive/MyDrive/MASc/Thesis/Quantum/Robustness Project/Datasets/1_phase_to_ground/standard_scaler_noGaussian.pkl", "pca_path": "/content/drive/MyDrive/MASc/Thesis/Quantum/Robustness Project/Datasets/1_phase_to_ground/PCA/pca_model_PCA_6_noGaussian.pkl", "data_min": -12.913997480535468, "data_max": 12.858614958109097, "loss_fn": "BCELoss", "optimizer": "Adam", "early_stopping_patience": 5, "results_path": "/content/drive/MyDrive/MASc/Thesis/Quantum/Robustness Project/SavedModels/1_phase_to_ground/PCA/PCA_6_noGaussian/CML_LSTM_stan_results.json", "model_path": "/content/drive/MyDrive/MASc/Thesis/Quantum/Robustness Project/SavedModels/1_phase_to_ground/PCA/PCA_6_noGaussian/CML_LSTM_stan_0.01lr_50epochs_256batch_size_1layers_64hidden_LSTM.pth"}, "performance_of_model": "CML_LSTM_stan_0.01lr_50epochs_256batch_size_1layers_64hidden", "performance_of_model_path": "/content/drive/MyDrive/MASc/Thesis/Quantum/Robustness Project/SavedModels/1_phase_to_ground/PCA/PCA_6_noGaussian/CML_LSTM_stan_0.01lr_50epochs_256batch_size_1layers_64hidden_LSTM.pth", "attack_adv_from": "CML_ResNet34_stan_0.001lr_50epochs_128batch_size", "attack_adv_from_path": "/content/drive/MyDrive/MASc/Thesis/Quantum/Robustness Project/SavedModels/1_phase_to_ground/PCA/PCA_6_noGaussian/CML_ResNet34_stan_0.001lr_50epochs_128batch_size"}, "metrics": {"0.0": {"accuracy": 0.9992521966722752, "recall": 0.9892761394101877, "precision": 1.0, "f1": 0.9946091644204852, "cm": [[4976, 0], [4, 369]]}, "0.05": {"accuracy": 0.9992521966722752, "recall": 0.9892761394101877, "precision": 1.0, "f1": 0.9946091644204852, "cm": [[4976, 0], [4, 369]]}, "0.1": {"accuracy": 0.9986913441764815, "recall": 0.9865951742627346, "precision": 0.9945945945945946, "f1": 0.990578734858681, "cm": [[4974, 2], [5, 368]]}, "0.15": {"accuracy": 0.9829874742942606, "recall": 0.9865951742627346, "precision": 0.8105726872246696, "f1": 0.8899637243047158, "cm": [[4890, 86], [5, 368]]}, "0.2": {"accuracy": 0.8846513366984483, "recall": 0.9865951742627346, "precision": 0.37551020408163266, "f1": 0.5439763488543976, "cm": [[4364, 612], [5, 368]]}, "0.25": {"accuracy": 0.7162086371284352, "recall": 0.9865951742627346, "precision": 0.19564061669324828, "f1": 0.32653061224489793, "cm": [[3463, 1513], [5, 368]]}, "0.3": {"accuracy": 0.5057020003739017, "recall": 0.9865951742627346, "precision": 0.12238111074160293, "f1": 0.21775147928994082, "cm": [[2337, 2639], [5, 368]]}, "0.35": {"accuracy": 0.430173864273696, "recall": 0.9865951742627346, "precision": 0.10788625036646145, "f1": 0.1945031712473573, "cm": [[1933, 3043], [5, 368]]}, "0.4": {"accuracy": 0.4118526827444382, "recall": 0.9865951742627346, "precision": 0.1048731832430892, "f1": 0.18959299330242144, "cm": [[1835, 3141], [5, 368]]}, "0.45": {"accuracy": 0.3847448121144139, "recall": 0.9865951742627346, "precision": 0.10071154898741105, "f1": 0.18276632729078718, "cm": [[1690, 3286], [5, 368]]}, "0.5": {"accuracy": 0.36006730229949524, "recall": 0.9865951742627346, "precision": 0.09720021130480719, "f1": 0.17696561673479203, "cm": [[1558, 3418], [5, 368]]}, "0.55": {"accuracy": 0.3481024490558983, "recall": 0.9865951742627346, "precision": 0.09558441558441559, "f1": 0.17428368458441865, "cm": [[1494, 3482], [5, 368]]}, "0.6": {"accuracy": 0.33295943166947095, "recall": 0.9865951742627346, "precision": 0.09361485627066904, "f1": 0.17100371747211895, "cm": [[1413, 3563], [5, 368]]}, "0.65": {"accuracy": 0.319125070106562, "recall": 0.9892761394101877, "precision": 0.09208884452208635, "f1": 0.1684931506849315, "cm": [[1338, 3638], [4, 369]]}, "0.7": {"accuracy": 0.3129556926528323, "recall": 0.9919571045576407, "precision": 0.09153884215734785, "f1": 0.16761041902604756, "cm": [[1304, 3672], [3, 370]]}, "0.75": {"accuracy": 0.30042998691344175, "recall": 0.9919571045576407, "precision": 0.09004623996106109, "f1": 0.1651048639000446, "cm": [[1237, 3739], [3, 370]]}, "0.8": {"accuracy": 0.2677135913254814, "recall": 0.9919571045576407, "precision": 0.08636788048552754, "f1": 0.15890057977238567, "cm": [[1062, 3914], [3, 370]]}, "0.85": {"accuracy": 0.22976257244344736, "recall": 0.9946380697050938, "precision": 0.08264646914680329, "f1": 0.15261209378856438, "cm": [[858, 4118], [2, 371]]}, "0.9": {"accuracy": 0.1856421761076837, "recall": 0.9946380697050938, "precision": 0.07851851851851852, "f1": 0.14554727344056492, "cm": [[622, 4354], [2, 371]]}}}